omnicloud/fastapi/__init__.py
omnicloud/fastapi/_app.py
omnicloud_fastapi-0.0.1.dist-info/LICENSE
omnicloud_fastapi-0.0.1.dist-info/METADATA
omnicloud_fastapi-0.0.1.dist-info/WHEEL
omnicloud_fastapi-0.0.1.dist-info/RECORD
