Metadata-Version: 2.1
Name: omnicloud-fastapi
Version: 0.0.1
Summary: Preconfigured FastAPI for Omnicloud
Home-page: https://omnicloud.world/apps
Keywords: omnicloud,supercloud,multicloud,cloud computing,migration,fastapi
Author: Iurii Tarasenko
Author-email: iurii@omnicloud.world
Requires-Python: >=3.10,<4.0
Classifier: Framework :: FastAPI
Classifier: Intended Audience :: Developers
Classifier: Intended Audience :: Information Technology
Classifier: License :: OSI Approved :: MIT License
Classifier: Programming Language :: Python :: 3
Classifier: Programming Language :: Python :: 3.10
Classifier: Programming Language :: Python :: 3.11
Classifier: Programming Language :: Python :: 3.10
Classifier: Topic :: Software Development :: Libraries :: Python Modules
Requires-Dist: fastapi (>=0.95.0,<0.96.0)
Project-URL: Documentation, https://docs.omnicloud.world/app-fastapi
Project-URL: Repository, https://github.com/omnicloudworld/app.fastapi
